{
  "version": "7",
  "dialect": "postgresql",
  "entries": [
    {
      "idx": 0,
      "version": "7",
      "when": 1780931039744,
      "tag": "0000_silky_sally_floyd",
      "breakpoints": true
    },
    {
      "idx": 1,
      "version": "7",
      "when": 1780931039745,
      "tag": "0001_routes_geom_generic",
      "breakpoints": false
    },
    {
      "idx": 2,
      "version": "7",
      "when": 1780943906945,
      "tag": "0002_last_blue_blade",
      "breakpoints": true
    },
    {
      "idx": 3,
      "version": "7",
      "when": 1780944037490,
      "tag": "0003_misty_payback",
      "breakpoints": true
    },
    {
      "idx": 4,
      "version": "7",
      "when": 1780948052212,
      "tag": "0004_lyrical_miracleman",
      "breakpoints": true
    },
    {
      "idx": 5,
      "version": "7",
      "when": 1781037260123,
      "tag": "0005_sharp_spyke",
      "breakpoints": true
    },
    {
      "idx": 6,
      "version": "7",
      "when": 1781123660123,
      "tag": "0006_enable_rls",
      "breakpoints": true
    },
    {
      "idx": 7,
      "version": "7",
      "when": 1781115219888,
      "tag": "0007_dear_the_watchers",
      "breakpoints": true
    },
    {
      "idx": 8,
      "version": "7",
      "when": 1781390230579,
      "tag": "0008_glamorous_fixer",
      "breakpoints": true
    },
    {
      "idx": 9,
      "version": "7",
      "when": 1781427712066,
      "tag": "0009_rich_redwing",
      "breakpoints": true
    },
    {
      "idx": 10,
      "version": "7",
      "when": 1781472115963,
      "tag": "0010_majestic_fenris",
      "breakpoints": true
    }
  ]
}